<list>
  <geneticGame.BarrierSkeleton>
    <s>
      <x>549</x>
      <y>2</y>
    </s>
    <lenght>1095</lenght>
    <width>3</width>
    <angle>0.0</angle>
  </geneticGame.BarrierSkeleton>
  <geneticGame.BarrierSkeleton>
    <s>
      <x>3</x>
      <y>399</y>
    </s>
    <lenght>3</lenght>
    <width>796</width>
    <angle>0.0</angle>
  </geneticGame.BarrierSkeleton>
  <geneticGame.BarrierSkeleton>
    <s>
      <x>551</x>
      <y>791</y>
    </s>
    <lenght>1092</lenght>
    <width>9</width>
    <angle>0.0</angle>
  </geneticGame.BarrierSkeleton>
  <geneticGame.BarrierSkeleton>
    <s>
      <x>1095</x>
      <y>395</y>
    </s>
    <lenght>4</lenght>
    <width>782</width>
    <angle>0.0</angle>
  </geneticGame.BarrierSkeleton>
  <geneticGame.BarrierSkeleton>
    <s>
      <x>453</x>
      <y>34</y>
    </s>
    <lenght>25</lenght>
    <width>133</width>
    <angle>1.8771016105199014</angle>
  </geneticGame.BarrierSkeleton>
  <geneticGame.BarrierSkeleton>
    <s>
      <x>193</x>
      <y>102</y>
    </s>
    <lenght>383</lenght>
    <width>19</width>
    <angle>3.141592653589793</angle>
  </geneticGame.BarrierSkeleton>
  <geneticGame.BarrierSkeleton>
    <s>
      <x>569</x>
      <y>101</y>
    </s>
    <lenght>20</lenght>
    <width>152</width>
    <angle>2.2187498115977915</angle>
  </geneticGame.BarrierSkeleton>
  <geneticGame.BarrierSkeleton>
    <s>
      <x>649</x>
      <y>214</y>
    </s>
    <lenght>20</lenght>
    <width>144</width>
    <angle>2.8902652413026098</angle>
  </geneticGame.BarrierSkeleton>
  <geneticGame.BarrierSkeleton>
    <s>
      <x>452</x>
      <y>190</y>
    </s>
    <lenght>24</lenght>
    <width>243</width>
    <angle>2.356194490192345</angle>
  </geneticGame.BarrierSkeleton>
  <geneticGame.BarrierSkeleton>
    <s>
      <x>532</x>
      <y>305</y>
    </s>
    <lenght>25</lenght>
    <width>79</width>
    <angle>2.980586030093316</angle>
  </geneticGame.BarrierSkeleton>
  <geneticGame.BarrierSkeleton>
    <s>
      <x>667</x>
      <y>378</y>
    </s>
    <lenght>15</lenght>
    <width>197</width>
    <angle>3.102322745419921</angle>
  </geneticGame.BarrierSkeleton>
  <geneticGame.BarrierSkeleton>
    <s>
      <x>540</x>
      <y>411</y>
    </s>
    <lenght>18</lenght>
    <width>145</width>
    <angle>0.0</angle>
  </geneticGame.BarrierSkeleton>
  <geneticGame.BarrierSkeleton>
    <s>
      <x>581</x>
      <y>554</y>
    </s>
    <lenght>19</lenght>
    <width>168</width>
    <angle>5.749114556069322</angle>
  </geneticGame.BarrierSkeleton>
  <geneticGame.BarrierSkeleton>
    <s>
      <x>702</x>
      <y>654</y>
    </s>
    <lenght>230</lenght>
    <width>24</width>
    <angle>3.428262983229862</angle>
  </geneticGame.BarrierSkeleton>
  <geneticGame.BarrierSkeleton>
    <s>
      <x>891</x>
      <y>672</y>
    </s>
    <lenght>161</lenght>
    <width>24</width>
    <angle>6.0750547938792625</angle>
  </geneticGame.BarrierSkeleton>
  <geneticGame.BarrierSkeleton>
    <s>
      <x>957</x>
      <y>724</y>
    </s>
    <lenght>21</lenght>
    <width>133</width>
    <angle>0.0</angle>
  </geneticGame.BarrierSkeleton>
  <geneticGame.BarrierSkeleton>
    <s>
      <x>738</x>
      <y>505</y>
    </s>
    <lenght>28</lenght>
    <width>157</width>
    <angle>5.262167694762904</angle>
  </geneticGame.BarrierSkeleton>
  <geneticGame.BarrierSkeleton>
    <s>
      <x>866</x>
      <y>527</y>
    </s>
    <lenght>148</lenght>
    <width>34</width>
    <angle>2.9845130209103035</angle>
  </geneticGame.BarrierSkeleton>
  <geneticGame.BarrierSkeleton>
    <s>
      <x>1015</x>
      <y>515</y>
    </s>
    <lenght>159</lenght>
    <width>22</width>
    <angle>0.0</angle>
  </geneticGame.BarrierSkeleton>
  <geneticGame.BarrierSkeleton>
    <s>
      <x>363</x>
      <y>9</y>
    </s>
    <lenght>57</lenght>
    <width>13</width>
    <angle>0.2748893571891069</angle>
  </geneticGame.BarrierSkeleton>
</list>
<java.awt.Point>
  <x>-9</x>
  <y>-5</y>
</java.awt.Point>
